MANIFEST.in
README.md
setup.cfg
setup.py
./requirements.txt
cli/tumbo-cli.py
compose-files/docker-compose-app-docker_socket_exec.yml
compose-files/docker-compose-backup.yml
compose-files/docker-compose-base.yml
compose-files/docker-compose-db.yml
compose-files/docker-compose-rp.yml
compose-files/docker-compose-store.yml
k8s-files/cli/base.yml
k8s-files/cli/config.yml
k8s-files/cli/core.yml
k8s-files/cli/ingress.yml
k8s-files/cli/passwords.yml
k8s-files/cli/rp.yml
tumbo/__init__.py
tumbo/manage.py
tumbo/aaa/__init__.py
tumbo/aaa/admin.py
tumbo/aaa/models.py
tumbo/aaa/pipeline.py
tumbo/aaa/tests.py
tumbo/aaa/views.py
tumbo/aaa/cas/__init__.py
tumbo/aaa/cas/authentication.py
tumbo/aaa/cas/middleware.py
tumbo/aaa/cas/models.py
tumbo/aaa/cas/pipeline.py
tumbo/aaa/cas/urls.py
tumbo/aaa/cas/views.py
tumbo/aaa/migrations/0001_initial.py
tumbo/aaa/migrations/0002_ticket.py
tumbo/aaa/migrations/__init__.py
tumbo/aaa/templates/aaa/cas_loginpage.html
tumbo/aaa/templates/aaa/login_form.html
tumbo/aaa/templates/aaa/login_form_sa.html
tumbo/core/__init__.py
tumbo/core/admin.py
tumbo/core/api_authentication.py
tumbo/core/api_serializers.py
tumbo/core/api_urls.py
tumbo/core/api_views.py
tumbo/core/communication.py
tumbo/core/context_processors.py
tumbo/core/defaults.py
tumbo/core/importer.py
tumbo/core/loader.py
tumbo/core/log.py
tumbo/core/middleware.py
tumbo/core/models.py
tumbo/core/responses.py
tumbo/core/scheduler.py
tumbo/core/staticfiles.py
tumbo/core/tests.py
tumbo/core/threadpool.py
tumbo/core/urls.py
tumbo/core/userland_urls.py
tumbo/core/utils.py
tumbo/core/executors/__init__.py
tumbo/core/executors/async.py
tumbo/core/executors/heartbeat.py
tumbo/core/executors/remote.py
tumbo/core/executors/worker_engines/__init__.py
tumbo/core/executors/worker_engines/dockers.py
tumbo/core/executors/worker_engines/kube.py
tumbo/core/executors/worker_engines/rancher.py
tumbo/core/executors/worker_engines/spawnproc.py
tumbo/core/management/__init__.py
tumbo_server.egg-info/PKG-INFO
tumbo_server.egg-info/SOURCES.txt
tumbo_server.egg-info/dependency_links.txt
tumbo_server.egg-info/not-zip-safe
tumbo_server.egg-info/requires.txt
tumbo_server.egg-info/top_level.txt
