Metadata-Version: 1.0
Name: tumbo-server
Version: 0.4.12
Summary: Highly flexible Application Runtime Platform
Home-page: https://tumbo.io
Author: Philip Sahli
Author-email: philip@sahli.net
License: MIT
Platform: UNKNOWN
